{
  "main": {
    "id": "185c54ea47721cc9",
    "type": "split",
    "children": [
      {
        "id": "47386a5d0e9682bd",
        "type": "tabs",
        "children": [
          {
            "id": "6df13f973ba2ad97",
            "type": "leaf",
            "state": {
              "type": "markdown",
              "state": {
                "file": "2. Droit des personnes/Chapitre/T1 Chapitre 2 Perte de la Personalité juridique.md",
                "mode": "source",
                "source": false
              },
              "icon": "lucide-file",
              "title": "T1 Chapitre 2 Perte de la Personalité juridique"
            }
          },
          {
            "id": "1515b143fe21e9da",
            "type": "leaf",
            "state": {
              "type": "pdf",
              "state": {
                "file": "Livre/Jurisprence/Cour de Cassation, Assemblée plénière, du 31 mai 1991, 90-20.105, Publié au bulletin - Légifrance.pdf",
                "page": 1,
                "left": -8,
                "top": 338,
                "zoom": 1.92113768462671
              },
              "icon": "lucide-file-text",
              "title": "Cour de Cassation, Assemblée plénière, du 31 mai 1991, 90-20.105, Publié au bulletin - Légifrance"
            }
          },
          {
            "id": "2aaf628f3c887f8b",
            "type": "leaf",
            "dimension": 50,
            "state": {
              "type": "markdown",
              "state": {
                "file": "2. Droit des personnes/Chapitre/T1 Chapitre 1 Le début de la personalité juridique.md",
                "mode": "source",
                "source": false
              },
              "icon": "lucide-file",
              "title": "T1 Chapitre 1 Le début de la personalité juridique"
            }
          }
        ],
        "currentTab": 2
      }
    ],
    "direction": "vertical"
  },
  "left": {
    "id": "7e2c720d8b2152c5",
    "type": "split",
    "children": [
      {
        "id": "17fe3207ca4210fd",
        "type": "tabs",
        "children": [
          {
            "id": "3808da1c569404c4",
            "type": "leaf",
            "state": {
              "type": "file-explorer",
              "state": {
                "sortOrder": "alphabetical"
              },
              "icon": "lucide-folder-closed",
              "title": "Explorateur de fichiers"
            }
          },
          {
            "id": "b0075211be150954",
            "type": "leaf",
            "state": {
              "type": "search",
              "state": {
                "query": "",
                "matchingCase": false,
                "explainSearch": false,
                "collapseAll": false,
                "extraContext": false,
                "sortOrder": "alphabetical"
              },
              "icon": "lucide-search",
              "title": "Rechercher"
            }
          },
          {
            "id": "36b938b4c00d57a5",
            "type": "leaf",
            "state": {
              "type": "bookmarks",
              "state": {},
              "icon": "lucide-bookmark",
              "title": "Signet"
            }
          }
        ]
      }
    ],
    "direction": "horizontal",
    "width": 300
  },
  "right": {
    "id": "855d1de093254e10",
    "type": "split",
    "children": [
      {
        "id": "4b81170495a5a489",
        "type": "tabs",
        "children": [
          {
            "id": "9fe9f146e0030e37",
            "type": "leaf",
            "state": {
              "type": "backlink",
              "state": {
                "file": "2. Droit des personnes/Chapitre/T1 Chapitre 1 Le début de la personalité juridique.md",
                "collapseAll": false,
                "extraContext": false,
                "sortOrder": "alphabetical",
                "showSearch": false,
                "searchQuery": "",
                "backlinkCollapsed": false,
                "unlinkedCollapsed": true
              },
              "icon": "links-coming-in",
              "title": "Rétrolien pour T1 Chapitre 1 Le début de la personalité juridique"
            }
          },
          {
            "id": "937de7b0608879e7",
            "type": "leaf",
            "state": {
              "type": "outgoing-link",
              "state": {
                "file": "2. Droit des personnes/Chapitre/T1 Chapitre 1 Le début de la personalité juridique.md",
                "linksCollapsed": false,
                "unlinkedCollapsed": true
              },
              "icon": "links-going-out",
              "title": "Liens sortants de T1 Chapitre 1 Le début de la personalité juridique"
            }
          },
          {
            "id": "6ae75a53410954f4",
            "type": "leaf",
            "state": {
              "type": "tag",
              "state": {
                "sortOrder": "frequency",
                "useHierarchy": true
              },
              "icon": "lucide-tags",
              "title": "Mots-clés"
            }
          },
          {
            "id": "e900229c81df9900",
            "type": "leaf",
            "state": {
              "type": "outline",
              "state": {
                "file": "2. Droit des personnes/Chapitre/T1 Chapitre 1 Le début de la personalité juridique.md"
              },
              "icon": "lucide-list",
              "title": "Plan de T1 Chapitre 1 Le début de la personalité juridique"
            }
          }
        ]
      }
    ],
    "direction": "horizontal",
    "width": 300,
    "collapsed": true
  },
  "left-ribbon": {
    "hiddenItems": {
      "random-note:Ouvre une note au hasard": false,
      "audio-recorder:Démarrer / arrêter l'enregistrement": false,
      "switcher:Ouvrir le sélecteur rapide": false,
      "graph:Ouvrir la vue graphique": false,
      "canvas:Créer une nouvelle toile": false,
      "daily-notes:Ouvrir la note quotidienne": false,
      "templates:Insérer le modèle": false,
      "command-palette:Ouvrir la palette de commandes": false,
      "pdf-plus:PDF++: Toggle auto-copy": false,
      "pdf-plus:PDF++: Toggle auto-focus": false,
      "pdf-plus:PDF++: Toggle auto-paste": false
    }
  },
  "active": "2aaf628f3c887f8b",
  "lastOpenFiles": [
    "Livre/France/Code civil.pdf",
    "2. Droit des personnes/Chapitre/T1 Chapitre 2 Perte de la Personalité juridique.md",
    "Livre/Jurisprence/Cour de Cassation, Assemblée plénière, du 31 mai 1991, 90-20.105, Publié au bulletin - Légifrance.pdf",
    "2. Droit des personnes/Chapitre/T2 Chapitre 1 Le nom.md",
    "2. Droit des personnes/Chapitre/T2 Chapitre 2 Le prénom.md",
    "2. Droit des personnes/Chapitre/T2 Chapitre 3 Le sexe.md",
    "2. Droit des personnes/Chapitre/T2 Chapitre 4 Le Domicile.md",
    "2. Droit des personnes/Chapitre/T1 Chapitre 1 Le début de la personalité juridique.md",
    "2. Droit des personnes/Chapitre/T5 Chapitre 1 Le mineur.md",
    "2. Droit des personnes/Chapitre/T4 Chapitre 1 Protection de l'intégrité morale.md",
    "2. Droit des personnes/Chapitre/T3 Chapitre 1  L’intégrité physique.md",
    "3. Histoire du Droit/PERIODISATION HISTORIQUE.pdf",
    "3. Histoire du Droit/Histoire du Droit.md",
    "A. Exercice & Devoir rendu/Fiche d'arrêt entrainement.md",
    "Livre/Jurisprence/Cour de cassation, Assemblée plénière, 7 novembre 2014, 14-83.739.pdf",
    "9. Révisions et Fiches/Fiches de révision/Le tribunal paritaire des baux ruraux.md",
    "5. Introduction Général au Droit/Chapitre/P2 Chapitre 2 Mise en oeuvre du droit objectif.md",
    "2. Droit des personnes/Thème/THEME 5  LES PERSONNES VULNERABLE.md",
    "2. Droit des personnes/1. TD/Séance 4/Séance 4 Droit des personnes TD.md",
    "2. Droit des personnes/1. TD/Séance 4",
    "1. Droit Constitutionnel/Chapitre/T2 Chapitre 2. Les régimes parlementaires.md",
    "1. Droit Constitutionnel/1. TD/Séance 1-4/DM-S4/Correction Dissertation.md",
    "T2 Chapitre 2. Les régimes parlementaires.md",
    "Le tribunal paritaire des baux ruraux.md",
    "Correction Dissertation.md",
    "2. Droit des personnes/Thème/THEME 1 LA PERSONNALITE JURIDIQUE.md",
    "2. Droit des personnes/Droit des Personnes.md",
    "1. Droit Constitutionnel/Chapitre/T1 Chapitre 3. La constitution.md",
    "1. Droit Constitutionnel/Titre/Titre 1. Les fondements théoriques.md",
    "1. Droit Constitutionnel/Droit Constitutionnel.md",
    "1. Droit Constitutionnel/1. TD/Séance 1-4/Fiche-TD-seance1-4.pdf",
    "1. Droit Constitutionnel/1. TD/Séance 1-4/DM-S4",
    "Sans titre",
    "1. Droit Constitutionnel/1. TD/Séance 1-4/DM-S3",
    "5. Introduction Général au Droit/Topo en Asynchrone/Exercice/Séance 5 IGD 23-24 Asynchrone.pdf"
  ]
}